README.txt
setup.cfg
setup.py
avro/HandshakeRequest.avsc
avro/HandshakeResponse.avsc
avro/LICENSE
avro/NOTICE
avro/VERSION.txt
avro/__init__.py
avro/datafile.py
avro/io.py
avro/ipc.py
avro/protocol.py
avro/schema.py
avro/tool.py
avro/txipc.py
avro/tests/av_bench.py
avro/tests/gen_interop_data.py
avro/tests/run_tests.py
avro/tests/sample_http_client.py
avro/tests/sample_http_server.py
avro/tests/test_datafile.py
avro/tests/test_datafile_interop.py
avro/tests/test_enum.py
avro/tests/test_io.py
avro/tests/test_ipc.py
avro/tests/test_protocol.py
avro/tests/test_schema.py
avro/tests/test_script.py
avro/tests/txsample_http_client.py
avro/tests/txsample_http_server.py
avro_python3.egg-info/PKG-INFO
avro_python3.egg-info/SOURCES.txt
avro_python3.egg-info/dependency_links.txt
avro_python3.egg-info/top_level.txt
scripts/avro