Metadata-Version: 1.0
Name: avro-python3
Version: 1.8.0
Summary: Avro is a serialization and RPC framework.
Home-page: http://avro.apache.org/
Author: Apache Avro
Author-email: dev@avro.apache.org
License: Apache License 2.0
Keywords: avro serialization rpc
Platform: UNKNOWN
